{
    "player_name": "Abde Ezzalzouli",
    "player_id": "427283",
    "team": "home",
    "position": "ML",
    "shirtNo": 16,
    "height": 177,
    "weight": 73,
    "age": 22,
    "isFirstEleven": true,
    "isManOfTheMatch": false,
    "stats": {
        "possession": {
            "8": 1.0,
            "16": 1.0,
            "22": 1.0,
            "27": 1.0,
            "35": 2.0,
            "37": 1.0,
            "46": 1.0,
            "53": 1.0,
            "62": 1.0,
            "69": 2.0
        },
        "ratings": {
            "0": 6.0,
            "5": 5.97,
            "8": 6.05,
            "10": 6.07,
            "16": 6.07,
            "21": 6.26,
            "22": 6.26,
            "27": 6.42,
            "29": 6.54,
            "35": 6.54,
            "37": 6.54,
            "38": 6.68,
            "40": 6.82,
            "41": 6.81,
            "46": 6.81,
            "47": 6.79,
            "53": 6.8,
            "62": 6.8,
            "64": 6.84,
            "69": 6.93,
            "74": 7.06
        },
        "shotsTotal": {
            "38": 1.0
        },
        "shotsOffTarget": {
            "38": 1.0
        },
        "touches": {
            "5": 1.0,
            "8": 1.0,
            "10": 2.0,
            "16": 1.0,
            "21": 3.0,
            "22": 1.0,
            "27": 2.0,
            "35": 2.0,
            "37": 1.0,
            "38": 2.0,
            "40": 2.0,
            "46": 1.0,
            "53": 1.0,
            "62": 2.0,
            "64": 1.0,
            "69": 2.0
        },
        "passesTotal": {
            "8": 1.0,
            "16": 1.0,
            "22": 1.0,
            "35": 2.0,
            "37": 1.0,
            "46": 1.0,
            "53": 1.0,
            "62": 1.0,
            "69": 2.0,
            "27": 1.0
        },
        "passesAccurate": {
            "8": 1.0,
            "16": 1.0,
            "22": 1.0,
            "35": 2.0,
            "37": 1.0,
            "46": 1.0,
            "53": 1.0,
            "62": 1.0,
            "69": 2.0
        },
        "passesKey": {
            "8": 1.0,
            "69": 1.0
        },
        "passSuccess": {
            "8": 100.0,
            "16": 100.0,
            "22": 100.0,
            "35": 100.0,
            "37": 100.0,
            "46": 100.0,
            "53": 100.0,
            "62": 100.0,
            "69": 100.0,
            "27": 0.0
        },
        "aerialsTotal": {
            "47": 1.0
        },
        "offensiveAerials": {
            "47": 1.0
        },
        "foulsCommited": {
            "41": 1.0
        },
        "dribblesWon": {
            "21": 1.0,
            "27": 1.0,
            "38": 1.0,
            "40": 1.0
        },
        "dribblesAttempted": {
            "21": 2.0,
            "27": 1.0,
            "38": 1.0,
            "40": 2.0,
            "10": 1.0
        },
        "dribblesLost": {
            "10": 1.0,
            "21": 1.0,
            "40": 1.0
        },
        "dribbleSuccess": {
            "21": 50.0,
            "27": 100.0,
            "38": 100.0,
            "40": 50.0,
            "10": 0.0
        }
    },
    "events": [
        {
            "id": 2636696795.0,
            "eventId": 44,
            "minute": 5,
            "second": 30,
            "teamId": 495,
            "playerId": 427283,
            "x": 82.5,
            "y": 81.2,
            "expandedMinute": 5,
            "period": {
                "value": 1,
                "displayName": "FirstHalf"
            },
            "type": {
                "value": 61,
                "displayName": "BallTouch"
            },
            "outcomeType": {
                "value": 0,
                "displayName": "Unsuccessful"
            },
            "qualifiers": [
                {
                    "type": {
                        "value": 178,
                        "displayName": "StandingSave"
                    }
                },
                {
                    "type": {
                        "value": 56,
                        "displayName": "Zone"
                    },
                    "value": "Left"
                }
            ],
            "satisfiedEventsTypes": [
                91,
                69
            ],
            "isTouch": true
        },
        {
            "id": 2636697115.0,
            "eventId": 87,
            "minute": 8,
            "second": 53,
            "teamId": 495,
            "playerId": 427283,
            "x": 88.2,
            "y": 58.3,
            "expandedMinute": 8,
            "period": {
                "value": 1,
                "displayName": "FirstHalf"
            },
            "type": {
                "value": 1,
                "displayName": "Pass"
            },
            "outcomeType": {
                "value": 1,
                "displayName": "Successful"
            },
            "qualifiers": [
                {
                    "type": {
                        "value": 56,
                        "displayName": "Zone"
                    },
                    "value": "Center"
                },
                {
                    "type": {
                        "value": 141,
                        "displayName": "PassEndY"
                    },
                    "value": "50.8"
                },
                {
                    "type": {
                        "value": 3,
                        "displayName": "HeadPass"
                    }
                },
                {
                    "type": {
                        "value": 213,
                        "displayName": "Angle"
                    },
                    "value": "4.90"
                },
                {
                    "type": {
                        "value": 212,
                        "displayName": "Length"
                    },
                    "value": "5.2"
                },
                {
                    "type": {
                        "value": 140,
                        "displayName": "PassEndX"
                    },
                    "value": "89.1"
                },
                {
                    "type": {
                        "value": 154,
                        "displayName": "IntentionalAssist"
                    }
                },
                {
                    "type": {
                        "value": 210,
                        "displayName": "ShotAssist"
                    },
                    "value": "13"
                },
                {
                    "type": {
                        "value": 11113,
                        "displayName": "KeyPass"
                    }
                }
            ],
            "satisfiedEventsTypes": [
                91,
                119,
                117,
                30,
                123,
                139,
                205,
                40,
                46,
                36,
                38,
                217,
                218
            ],
            "isTouch": true,
            "endX": 89.1,
            "endY": 50.8
        },
        {
            "id": 2636697217.0,
            "eventId": 91,
            "minute": 10,
            "second": 14,
            "teamId": 495,
            "playerId": 427283,
            "x": 61.6,
            "y": 79.2,
            "expandedMinute": 10,
            "period": {
                "value": 1,
                "displayName": "FirstHalf"
            },
            "type": {
                "value": 4,
                "displayName": "Foul"
            },
            "outcomeType": {
                "value": 1,
                "displayName": "Successful"
            },
            "qualifiers": [
                {
                    "type": {
                        "value": 13,
                        "displayName": "Foul"
                    }
                },
                {
                    "type": {
                        "value": 233,
                        "displayName": "OppositeRelatedEvent"
                    },
                    "value": "91"
                },
                {
                    "type": {
                        "value": 286,
                        "displayName": "Offensive"
                    }
                },
                {
                    "type": {
                        "value": 56,
                        "displayName": "Zone"
                    },
                    "value": "Left"
                }
            ],
            "satisfiedEventsTypes": [
                91,
                63
            ],
            "isTouch": true
        },
        {
            "id": 2636697235.0,
            "eventId": 96,
            "minute": 10,
            "second": 54,
            "teamId": 495,
            "playerId": 427283,
            "x": 87.4,
            "y": 95.6,
            "expandedMinute": 10,
            "period": {
                "value": 1,
                "displayName": "FirstHalf"
            },
            "type": {
                "value": 3,
                "displayName": "TakeOn"
            },
            "outcomeType": {
                "value": 0,
                "displayName": "Unsuccessful"
            },
            "qualifiers": [
                {
                    "type": {
                        "value": 56,
                        "displayName": "Zone"
                    },
                    "value": "Left"
                },
                {
                    "type": {
                        "value": 286,
                        "displayName": "Offensive"
                    }
                },
                {
                    "type": {
                        "value": 233,
                        "displayName": "OppositeRelatedEvent"
                    },
                    "value": "92"
                },
                {
                    "type": {
                        "value": 178,
                        "displayName": "StandingSave"
                    }
                }
            ],
            "satisfiedEventsTypes": [
                91,
                53
            ],
            "isTouch": true
        },
        {
            "id": 2636697675.0,
            "eventId": 146,
            "minute": 16,
            "second": 46,
            "teamId": 495,
            "playerId": 427283,
            "x": 64.1,
            "y": 80.6,
            "expandedMinute": 16,
            "period": {
                "value": 1,
                "displayName": "FirstHalf"
            },
            "type": {
                "value": 1,
                "displayName": "Pass"
            },
            "outcomeType": {
                "value": 1,
                "displayName": "Successful"
            },
            "qualifiers": [
                {
                    "type": {
                        "value": 140,
                        "displayName": "PassEndX"
                    },
                    "value": "51.7"
                },
                {
                    "type": {
                        "value": 212,
                        "displayName": "Length"
                    },
                    "value": "13.5"
                },
                {
                    "type": {
                        "value": 213,
                        "displayName": "Angle"
                    },
                    "value": "3.42"
                },
                {
                    "type": {
                        "value": 141,
                        "displayName": "PassEndY"
                    },
                    "value": "75.1"
                },
                {
                    "type": {
                        "value": 178,
                        "displayName": "StandingSave"
                    }
                },
                {
                    "type": {
                        "value": 56,
                        "displayName": "Zone"
                    },
                    "value": "Center"
                }
            ],
            "satisfiedEventsTypes": [
                91,
                119,
                117,
                30,
                35,
                38,
                216,
                218
            ],
            "isTouch": true,
            "endX": 51.7,
            "endY": 75.1
        },
        {
            "id": 2636698155.0,
            "eventId": 218,
            "minute": 21,
            "second": 3,
            "teamId": 495,
            "playerId": 427283,
            "x": 30.2,
            "y": 96.2,
            "expandedMinute": 21,
            "period": {
                "value": 1,
                "displayName": "FirstHalf"
            },
            "type": {
                "value": 3,
                "displayName": "TakeOn"
            },
            "outcomeType": {
                "value": 1,
                "displayName": "Successful"
            },
            "qualifiers": [
                {
                    "type": {
                        "value": 285,
                        "displayName": "Defensive"
                    }
                },
                {
                    "type": {
                        "value": 178,
                        "displayName": "StandingSave"
                    }
                },
                {
                    "type": {
                        "value": 56,
                        "displayName": "Zone"
                    },
                    "value": "Back"
                },
                {
                    "type": {
                        "value": 233,
                        "displayName": "OppositeRelatedEvent"
                    },
                    "value": "212"
                }
            ],
            "satisfiedEventsTypes": [
                91,
                54
            ],
            "isTouch": true
        },
        {
            "id": 2636772265.0,
            "eventId": 824,
            "minute": 21,
            "second": 7,
            "teamId": 495,
            "playerId": 427283,
            "x": 56.6,
            "y": 95.4,
            "expandedMinute": 21,
            "period": {
                "value": 1,
                "displayName": "FirstHalf"
            },
            "type": {
                "value": 3,
                "displayName": "TakeOn"
            },
            "outcomeType": {
                "value": 0,
                "displayName": "Unsuccessful"
            },
            "qualifiers": [
                {
                    "type": {
                        "value": 178,
                        "displayName": "StandingSave"
                    }
                },
                {
                    "type": {
                        "value": 56,
                        "displayName": "Zone"
                    },
                    "value": "Left"
                },
                {
                    "type": {
                        "value": 286,
                        "displayName": "Offensive"
                    }
                }
            ],
            "satisfiedEventsTypes": [
                91,
                53
            ],
            "isTouch": true
        },
        {
            "id": 2636698157.0,
            "eventId": 219,
            "minute": 21,
            "second": 8,
            "teamId": 495,
            "playerId": 427283,
            "x": 56.7,
            "y": 96.8,
            "expandedMinute": 21,
            "period": {
                "value": 1,
                "displayName": "FirstHalf"
            },
            "type": {
                "value": 4,
                "displayName": "Foul"
            },
            "outcomeType": {
                "value": 1,
                "displayName": "Successful"
            },
            "qualifiers": [
                {
                    "type": {
                        "value": 13,
                        "displayName": "Foul"
                    }
                },
                {
                    "type": {
                        "value": 286,
                        "displayName": "Offensive"
                    }
                },
                {
                    "type": {
                        "value": 56,
                        "displayName": "Zone"
                    },
                    "value": "Left"
                },
                {
                    "type": {
                        "value": 233,
                        "displayName": "OppositeRelatedEvent"
                    },
                    "value": "213"
                }
            ],
            "satisfiedEventsTypes": [
                91,
                63
            ],
            "isTouch": true
        },
        {
            "id": 2636698223.0,
            "eventId": 227,
            "minute": 22,
            "second": 21,
            "teamId": 495,
            "playerId": 427283,
            "x": 68.2,
            "y": 81.2,
            "expandedMinute": 22,
            "period": {
                "value": 1,
                "displayName": "FirstHalf"
            },
            "type": {
                "value": 1,
                "displayName": "Pass"
            },
            "outcomeType": {
                "value": 1,
                "displayName": "Successful"
            },
            "qualifiers": [
                {
                    "type": {
                        "value": 140,
                        "displayName": "PassEndX"
                    },
                    "value": "68.7"
                },
                {
                    "type": {
                        "value": 141,
                        "displayName": "PassEndY"
                    },
                    "value": "67.0"
                },
                {
                    "type": {
                        "value": 56,
                        "displayName": "Zone"
                    },
                    "value": "Center"
                },
                {
                    "type": {
                        "value": 178,
                        "displayName": "StandingSave"
                    }
                },
                {
                    "type": {
                        "value": 213,
                        "displayName": "Angle"
                    },
                    "value": "4.77"
                },
                {
                    "type": {
                        "value": 212,
                        "displayName": "Length"
                    },
                    "value": "9.7"
                }
            ],
            "satisfiedEventsTypes": [
                91,
                119,
                117,
                30,
                205,
                36,
                38,
                217,
                218
            ],
            "isTouch": true,
            "endX": 68.7,
            "endY": 67.0
        },
        {
            "id": 2636698573.0,
            "eventId": 270,
            "minute": 27,
            "second": 29,
            "teamId": 495,
            "playerId": 427283,
            "x": 81.0,
            "y": 92.4,
            "expandedMinute": 27,
            "period": {
                "value": 1,
                "displayName": "FirstHalf"
            },
            "type": {
                "value": 3,
                "displayName": "TakeOn"
            },
            "outcomeType": {
                "value": 1,
                "displayName": "Successful"
            },
            "qualifiers": [
                {
                    "type": {
                        "value": 178,
                        "displayName": "StandingSave"
                    }
                },
                {
                    "type": {
                        "value": 286,
                        "displayName": "Offensive"
                    }
                },
                {
                    "type": {
                        "value": 56,
                        "displayName": "Zone"
                    },
                    "value": "Left"
                },
                {
                    "type": {
                        "value": 233,
                        "displayName": "OppositeRelatedEvent"
                    },
                    "value": "240"
                }
            ],
            "satisfiedEventsTypes": [
                91,
                54
            ],
            "isTouch": true
        },
        {
            "id": 2636698575.0,
            "eventId": 271,
            "minute": 27,
            "second": 33,
            "teamId": 495,
            "playerId": 427283,
            "x": 96.5,
            "y": 73.2,
            "expandedMinute": 27,
            "period": {
                "value": 1,
                "displayName": "FirstHalf"
            },
            "type": {
                "value": 1,
                "displayName": "Pass"
            },
            "outcomeType": {
                "value": 0,
                "displayName": "Unsuccessful"
            },
            "qualifiers": [
                {
                    "type": {
                        "value": 286,
                        "displayName": "Offensive"
                    }
                },
                {
                    "type": {
                        "value": 233,
                        "displayName": "OppositeRelatedEvent"
                    },
                    "value": "241"
                },
                {
                    "type": {
                        "value": 212,
                        "displayName": "Length"
                    },
                    "value": "3.5"
                },
                {
                    "type": {
                        "value": 178,
                        "displayName": "StandingSave"
                    }
                },
                {
                    "type": {
                        "value": 213,
                        "displayName": "Angle"
                    },
                    "value": "4.74"
                },
                {
                    "type": {
                        "value": 141,
                        "displayName": "PassEndY"
                    },
                    "value": "68.1"
                },
                {
                    "type": {
                        "value": 56,
                        "displayName": "Zone"
                    },
                    "value": "Center"
                },
                {
                    "type": {
                        "value": 140,
                        "displayName": "PassEndX"
                    },
                    "value": "96.6"
                }
            ],
            "satisfiedEventsTypes": [
                91,
                120,
                29,
                36,
                38,
                217,
                218
            ],
            "isTouch": true,
            "endX": 96.6,
            "endY": 68.1
        },
        {
            "id": 2636699009.0,
            "eventId": 311,
            "minute": 35,
            "second": 14,
            "teamId": 495,
            "playerId": 427283,
            "x": 53.7,
            "y": 95.0,
            "expandedMinute": 35,
            "period": {
                "value": 1,
                "displayName": "FirstHalf"
            },
            "type": {
                "value": 1,
                "displayName": "Pass"
            },
            "outcomeType": {
                "value": 1,
                "displayName": "Successful"
            },
            "qualifiers": [
                {
                    "type": {
                        "value": 141,
                        "displayName": "PassEndY"
                    },
                    "value": "94.8"
                },
                {
                    "type": {
                        "value": 56,
                        "displayName": "Zone"
                    },
                    "value": "Back"
                },
                {
                    "type": {
                        "value": 213,
                        "displayName": "Angle"
                    },
                    "value": "3.16"
                },
                {
                    "type": {
                        "value": 140,
                        "displayName": "PassEndX"
                    },
                    "value": "45.2"
                },
                {
                    "type": {
                        "value": 212,
                        "displayName": "Length"
                    },
                    "value": "8.9"
                }
            ],
            "satisfiedEventsTypes": [
                91,
                117,
                30,
                35,
                38,
                216,
                218
            ],
            "isTouch": true,
            "endX": 45.2,
            "endY": 94.8
        },
        {
            "id": 2636699025.0,
            "eventId": 313,
            "minute": 35,
            "second": 19,
            "teamId": 495,
            "playerId": 427283,
            "x": 50.6,
            "y": 90.8,
            "expandedMinute": 35,
            "period": {
                "value": 1,
                "displayName": "FirstHalf"
            },
            "type": {
                "value": 1,
                "displayName": "Pass"
            },
            "outcomeType": {
                "value": 1,
                "displayName": "Successful"
            },
            "qualifiers": [
                {
                    "type": {
                        "value": 213,
                        "displayName": "Angle"
                    },
                    "value": "4.51"
                },
                {
                    "type": {
                        "value": 212,
                        "displayName": "Length"
                    },
                    "value": "9.2"
                },
                {
                    "type": {
                        "value": 56,
                        "displayName": "Zone"
                    },
                    "value": "Back"
                },
                {
                    "type": {
                        "value": 140,
                        "displayName": "PassEndX"
                    },
                    "value": "48.8"
                },
                {
                    "type": {
                        "value": 178,
                        "displayName": "StandingSave"
                    }
                },
                {
                    "type": {
                        "value": 141,
                        "displayName": "PassEndY"
                    },
                    "value": "77.5"
                }
            ],
            "satisfiedEventsTypes": [
                91,
                117,
                30,
                35,
                38,
                216,
                218
            ],
            "isTouch": true,
            "endX": 48.8,
            "endY": 77.5
        },
        {
            "id": 2636699181.0,
            "eventId": 328,
            "minute": 37,
            "second": 1,
            "teamId": 495,
            "playerId": 427283,
            "x": 61.7,
            "y": 96.1,
            "expandedMinute": 37,
            "period": {
                "value": 1,
                "displayName": "FirstHalf"
            },
            "type": {
                "value": 1,
                "displayName": "Pass"
            },
            "outcomeType": {
                "value": 1,
                "displayName": "Successful"
            },
            "qualifiers": [
                {
                    "type": {
                        "value": 212,
                        "displayName": "Length"
                    },
                    "value": "10.2"
                },
                {
                    "type": {
                        "value": 56,
                        "displayName": "Zone"
                    },
                    "value": "Left"
                },
                {
                    "type": {
                        "value": 141,
                        "displayName": "PassEndY"
                    },
                    "value": "91.1"
                },
                {
                    "type": {
                        "value": 140,
                        "displayName": "PassEndX"
                    },
                    "value": "52.5"
                },
                {
                    "type": {
                        "value": 213,
                        "displayName": "Angle"
                    },
                    "value": "3.48"
                },
                {
                    "type": {
                        "value": 178,
                        "displayName": "StandingSave"
                    }
                }
            ],
            "satisfiedEventsTypes": [
                91,
                119,
                117,
                30,
                35,
                38,
                216,
                218
            ],
            "isTouch": true,
            "endX": 52.5,
            "endY": 91.1
        },
        {
            "id": 2636699287.0,
            "eventId": 343,
            "minute": 38,
            "second": 13,
            "teamId": 495,
            "playerId": 427283,
            "x": 90.7,
            "y": 66.3,
            "expandedMinute": 38,
            "period": {
                "value": 1,
                "displayName": "FirstHalf"
            },
            "type": {
                "value": 3,
                "displayName": "TakeOn"
            },
            "outcomeType": {
                "value": 1,
                "displayName": "Successful"
            },
            "qualifiers": [
                {
                    "type": {
                        "value": 56,
                        "displayName": "Zone"
                    },
                    "value": "Center"
                },
                {
                    "type": {
                        "value": 233,
                        "displayName": "OppositeRelatedEvent"
                    },
                    "value": "295"
                },
                {
                    "type": {
                        "value": 286,
                        "displayName": "Offensive"
                    }
                },
                {
                    "type": {
                        "value": 178,
                        "displayName": "StandingSave"
                    }
                }
            ],
            "satisfiedEventsTypes": [
                91,
                54
            ],
            "isTouch": true
        },
        {
            "id": 2636699291.0,
            "eventId": 344,
            "minute": 38,
            "second": 14,
            "teamId": 495,
            "playerId": 427283,
            "relatedEventId": 342,
            "relatedPlayerId": 236519,
            "x": 92.4,
            "y": 66.3,
            "expandedMinute": 38,
            "period": {
                "value": 1,
                "displayName": "FirstHalf"
            },
            "type": {
                "value": 13,
                "displayName": "MissedShots"
            },
            "outcomeType": {
                "value": 1,
                "displayName": "Successful"
            },
            "qualifiers": [
                {
                    "type": {
                        "value": 72,
                        "displayName": "LeftFoot"
                    }
                },
                {
                    "type": {
                        "value": 154,
                        "displayName": "IntentionalAssist"
                    }
                },
                {
                    "type": {
                        "value": 56,
                        "displayName": "Zone"
                    },
                    "value": "Center"
                },
                {
                    "type": {
                        "value": 29,
                        "displayName": "Assisted"
                    }
                },
                {
                    "type": {
                        "value": 215,
                        "displayName": "IndividualPlay"
                    }
                },
                {
                    "type": {
                        "value": 64,
                        "displayName": "BoxLeft"
                    }
                },
                {
                    "type": {
                        "value": 74,
                        "displayName": "MissHigh"
                    }
                },
                {
                    "type": {
                        "value": 103,
                        "displayName": "GoalMouthZ"
                    },
                    "value": "84.7"
                },
                {
                    "type": {
                        "value": 178,
                        "displayName": "StandingSave"
                    }
                },
                {
                    "type": {
                        "value": 22,
                        "displayName": "RegularPlay"
                    }
                },
                {
                    "type": {
                        "value": 102,
                        "displayName": "GoalMouthY"
                    },
                    "value": "51.6"
                },
                {
                    "type": {
                        "value": 55,
                        "displayName": "RelatedEventId"
                    },
                    "value": "342"
                }
            ],
            "satisfiedEventsTypes": [
                91,
                7,
                90,
                10,
                1,
                3,
                13
            ],
            "isTouch": true,
            "goalMouthZ": 84.7,
            "goalMouthY": 51.6,
            "isShot": true
        },
        {
            "id": 2636699481.0,
            "eventId": 378,
            "minute": 40,
            "second": 13,
            "teamId": 495,
            "playerId": 427283,
            "x": 63.6,
            "y": 96.8,
            "expandedMinute": 40,
            "period": {
                "value": 1,
                "displayName": "FirstHalf"
            },
            "type": {
                "value": 3,
                "displayName": "TakeOn"
            },
            "outcomeType": {
                "value": 1,
                "displayName": "Successful"
            },
            "qualifiers": [
                {
                    "type": {
                        "value": 178,
                        "displayName": "StandingSave"
                    }
                },
                {
                    "type": {
                        "value": 233,
                        "displayName": "OppositeRelatedEvent"
                    },
                    "value": "311"
                },
                {
                    "type": {
                        "value": 286,
                        "displayName": "Offensive"
                    }
                },
                {
                    "type": {
                        "value": 56,
                        "displayName": "Zone"
                    },
                    "value": "Left"
                }
            ],
            "satisfiedEventsTypes": [
                91,
                54
            ],
            "isTouch": true
        },
        {
            "id": 2636699485.0,
            "eventId": 379,
            "minute": 40,
            "second": 16,
            "teamId": 495,
            "playerId": 427283,
            "x": 74.9,
            "y": 86.0,
            "expandedMinute": 40,
            "period": {
                "value": 1,
                "displayName": "FirstHalf"
            },
            "type": {
                "value": 3,
                "displayName": "TakeOn"
            },
            "outcomeType": {
                "value": 0,
                "displayName": "Unsuccessful"
            },
            "qualifiers": [
                {
                    "type": {
                        "value": 286,
                        "displayName": "Offensive"
                    }
                },
                {
                    "type": {
                        "value": 56,
                        "displayName": "Zone"
                    },
                    "value": "Left"
                },
                {
                    "type": {
                        "value": 233,
                        "displayName": "OppositeRelatedEvent"
                    },
                    "value": "312"
                },
                {
                    "type": {
                        "value": 178,
                        "displayName": "StandingSave"
                    }
                }
            ],
            "satisfiedEventsTypes": [
                91,
                53
            ],
            "isTouch": true
        },
        {
            "id": 2636699583.0,
            "eventId": 387,
            "minute": 41,
            "second": 42,
            "teamId": 495,
            "playerId": 427283,
            "x": 86.6,
            "y": 96.5,
            "expandedMinute": 41,
            "period": {
                "value": 1,
                "displayName": "FirstHalf"
            },
            "type": {
                "value": 4,
                "displayName": "Foul"
            },
            "outcomeType": {
                "value": 0,
                "displayName": "Unsuccessful"
            },
            "qualifiers": [
                {
                    "type": {
                        "value": 286,
                        "displayName": "Offensive"
                    }
                },
                {
                    "type": {
                        "value": 13,
                        "displayName": "Foul"
                    }
                },
                {
                    "type": {
                        "value": 178,
                        "displayName": "StandingSave"
                    }
                },
                {
                    "type": {
                        "value": 233,
                        "displayName": "OppositeRelatedEvent"
                    },
                    "value": "336"
                },
                {
                    "type": {
                        "value": 56,
                        "displayName": "Zone"
                    },
                    "value": "Left"
                }
            ],
            "satisfiedEventsTypes": [
                64
            ],
            "isTouch": false
        },
        {
            "id": 2636700129.0,
            "eventId": 433,
            "minute": 46,
            "second": 44,
            "teamId": 495,
            "playerId": 427283,
            "x": 45.9,
            "y": 95.4,
            "expandedMinute": 46,
            "period": {
                "value": 1,
                "displayName": "FirstHalf"
            },
            "type": {
                "value": 1,
                "displayName": "Pass"
            },
            "outcomeType": {
                "value": 1,
                "displayName": "Successful"
            },
            "qualifiers": [
                {
                    "type": {
                        "value": 140,
                        "displayName": "PassEndX"
                    },
                    "value": "23.2"
                },
                {
                    "type": {
                        "value": 178,
                        "displayName": "StandingSave"
                    }
                },
                {
                    "type": {
                        "value": 141,
                        "displayName": "PassEndY"
                    },
                    "value": "86.2"
                },
                {
                    "type": {
                        "value": 213,
                        "displayName": "Angle"
                    },
                    "value": "3.40"
                },
                {
                    "type": {
                        "value": 212,
                        "displayName": "Length"
                    },
                    "value": "24.6"
                },
                {
                    "type": {
                        "value": 56,
                        "displayName": "Zone"
                    },
                    "value": "Back"
                }
            ],
            "satisfiedEventsTypes": [
                91,
                117,
                30,
                35,
                38,
                215,
                218
            ],
            "isTouch": true,
            "endX": 23.2,
            "endY": 86.2
        },
        {
            "id": 2636700189.0,
            "eventId": 443,
            "minute": 47,
            "second": 20,
            "teamId": 495,
            "playerId": 427283,
            "x": 58.9,
            "y": 95.6,
            "expandedMinute": 47,
            "period": {
                "value": 1,
                "displayName": "FirstHalf"
            },
            "type": {
                "value": 44,
                "displayName": "Aerial"
            },
            "outcomeType": {
                "value": 0,
                "displayName": "Unsuccessful"
            },
            "qualifiers": [
                {
                    "type": {
                        "value": 233,
                        "displayName": "OppositeRelatedEvent"
                    },
                    "value": "381"
                },
                {
                    "type": {
                        "value": 56,
                        "displayName": "Zone"
                    },
                    "value": "Left"
                },
                {
                    "type": {
                        "value": 286,
                        "displayName": "Offensive"
                    }
                }
            ],
            "satisfiedEventsTypes": [
                198,
                199
            ],
            "isTouch": false
        },
        {
            "id": 2636703265.0,
            "eventId": 476,
            "minute": 49,
            "second": 28,
            "teamId": 495,
            "playerId": 427283,
            "x": 40.7,
            "y": 84.6,
            "expandedMinute": 53,
            "period": {
                "value": 2,
                "displayName": "SecondHalf"
            },
            "type": {
                "value": 1,
                "displayName": "Pass"
            },
            "outcomeType": {
                "value": 1,
                "displayName": "Successful"
            },
            "qualifiers": [
                {
                    "type": {
                        "value": 178,
                        "displayName": "StandingSave"
                    }
                },
                {
                    "type": {
                        "value": 213,
                        "displayName": "Angle"
                    },
                    "value": "3.07"
                },
                {
                    "type": {
                        "value": 212,
                        "displayName": "Length"
                    },
                    "value": "14.3"
                },
                {
                    "type": {
                        "value": 56,
                        "displayName": "Zone"
                    },
                    "value": "Back"
                },
                {
                    "type": {
                        "value": 141,
                        "displayName": "PassEndY"
                    },
                    "value": "86.2"
                },
                {
                    "type": {
                        "value": 140,
                        "displayName": "PassEndX"
                    },
                    "value": "27.1"
                }
            ],
            "satisfiedEventsTypes": [
                91,
                117,
                30,
                35,
                37,
                215,
                218
            ],
            "isTouch": true,
            "endX": 27.1,
            "endY": 86.2
        },
        {
            "id": 2636705563.0,
            "eventId": 530,
            "minute": 58,
            "second": 9,
            "teamId": 495,
            "playerId": 427283,
            "x": 57.7,
            "y": 92.2,
            "expandedMinute": 62,
            "period": {
                "value": 2,
                "displayName": "SecondHalf"
            },
            "type": {
                "value": 74,
                "displayName": "BlockedPass"
            },
            "outcomeType": {
                "value": 1,
                "displayName": "Successful"
            },
            "qualifiers": [
                {
                    "type": {
                        "value": 56,
                        "displayName": "Zone"
                    },
                    "value": "Left"
                },
                {
                    "type": {
                        "value": 285,
                        "displayName": "Defensive"
                    }
                },
                {
                    "type": {
                        "value": 178,
                        "displayName": "StandingSave"
                    }
                },
                {
                    "type": {
                        "value": 233,
                        "displayName": "OppositeRelatedEvent"
                    },
                    "value": "510"
                }
            ],
            "satisfiedEventsTypes": [
                91,
                60
            ],
            "isTouch": true
        },
        {
            "id": 2636705829.0,
            "eventId": 540,
            "minute": 58,
            "second": 52,
            "teamId": 495,
            "playerId": 427283,
            "x": 39.7,
            "y": 94.4,
            "expandedMinute": 62,
            "period": {
                "value": 2,
                "displayName": "SecondHalf"
            },
            "type": {
                "value": 1,
                "displayName": "Pass"
            },
            "outcomeType": {
                "value": 1,
                "displayName": "Successful"
            },
            "qualifiers": [
                {
                    "type": {
                        "value": 213,
                        "displayName": "Angle"
                    },
                    "value": "5.57"
                },
                {
                    "type": {
                        "value": 141,
                        "displayName": "PassEndY"
                    },
                    "value": "75.0"
                },
                {
                    "type": {
                        "value": 140,
                        "displayName": "PassEndX"
                    },
                    "value": "54.1"
                },
                {
                    "type": {
                        "value": 178,
                        "displayName": "StandingSave"
                    }
                },
                {
                    "type": {
                        "value": 212,
                        "displayName": "Length"
                    },
                    "value": "20.1"
                },
                {
                    "type": {
                        "value": 56,
                        "displayName": "Zone"
                    },
                    "value": "Center"
                }
            ],
            "satisfiedEventsTypes": [
                91,
                119,
                117,
                30,
                36,
                38,
                216,
                218
            ],
            "isTouch": true,
            "endX": 54.1,
            "endY": 75.0
        },
        {
            "id": 2636706315.0,
            "eventId": 553,
            "minute": 60,
            "second": 19,
            "teamId": 495,
            "playerId": 427283,
            "x": 55.8,
            "y": 83.1,
            "expandedMinute": 64,
            "period": {
                "value": 2,
                "displayName": "SecondHalf"
            },
            "type": {
                "value": 49,
                "displayName": "BallRecovery"
            },
            "outcomeType": {
                "value": 1,
                "displayName": "Successful"
            },
            "qualifiers": [],
            "satisfiedEventsTypes": [
                93
            ],
            "isTouch": false
        },
        {
            "id": 2636706339.0,
            "eventId": 554,
            "minute": 60,
            "second": 21,
            "teamId": 495,
            "playerId": 427283,
            "x": 55.6,
            "y": 83.9,
            "expandedMinute": 64,
            "period": {
                "value": 2,
                "displayName": "SecondHalf"
            },
            "type": {
                "value": 4,
                "displayName": "Foul"
            },
            "outcomeType": {
                "value": 1,
                "displayName": "Successful"
            },
            "qualifiers": [
                {
                    "type": {
                        "value": 286,
                        "displayName": "Offensive"
                    }
                },
                {
                    "type": {
                        "value": 233,
                        "displayName": "OppositeRelatedEvent"
                    },
                    "value": "537"
                },
                {
                    "type": {
                        "value": 56,
                        "displayName": "Zone"
                    },
                    "value": "Left"
                },
                {
                    "type": {
                        "value": 13,
                        "displayName": "Foul"
                    }
                }
            ],
            "satisfiedEventsTypes": [
                91,
                63
            ],
            "isTouch": true
        },
        {
            "id": 2636708143.0,
            "eventId": 583,
            "minute": 65,
            "second": 48,
            "teamId": 495,
            "playerId": 427283,
            "x": 59.6,
            "y": 94.8,
            "expandedMinute": 69,
            "period": {
                "value": 2,
                "displayName": "SecondHalf"
            },
            "type": {
                "value": 1,
                "displayName": "Pass"
            },
            "outcomeType": {
                "value": 1,
                "displayName": "Successful"
            },
            "qualifiers": [
                {
                    "type": {
                        "value": 212,
                        "displayName": "Length"
                    },
                    "value": "18.2"
                },
                {
                    "type": {
                        "value": 178,
                        "displayName": "StandingSave"
                    }
                },
                {
                    "type": {
                        "value": 213,
                        "displayName": "Angle"
                    },
                    "value": "0.02"
                },
                {
                    "type": {
                        "value": 56,
                        "displayName": "Zone"
                    },
                    "value": "Left"
                },
                {
                    "type": {
                        "value": 140,
                        "displayName": "PassEndX"
                    },
                    "value": "76.9"
                },
                {
                    "type": {
                        "value": 141,
                        "displayName": "PassEndY"
                    },
                    "value": "95.3"
                }
            ],
            "satisfiedEventsTypes": [
                91,
                119,
                117,
                30,
                205,
                36,
                37,
                217,
                218
            ],
            "isTouch": true,
            "endX": 76.9,
            "endY": 95.3
        },
        {
            "id": 2636708197.0,
            "eventId": 585,
            "minute": 65,
            "second": 55,
            "teamId": 495,
            "playerId": 427283,
            "x": 90.2,
            "y": 72.2,
            "expandedMinute": 69,
            "period": {
                "value": 2,
                "displayName": "SecondHalf"
            },
            "type": {
                "value": 1,
                "displayName": "Pass"
            },
            "outcomeType": {
                "value": 1,
                "displayName": "Successful"
            },
            "qualifiers": [
                {
                    "type": {
                        "value": 212,
                        "displayName": "Length"
                    },
                    "value": "7.6"
                },
                {
                    "type": {
                        "value": 213,
                        "displayName": "Angle"
                    },
                    "value": "2.12"
                },
                {
                    "type": {
                        "value": 140,
                        "displayName": "PassEndX"
                    },
                    "value": "86.4"
                },
                {
                    "type": {
                        "value": 178,
                        "displayName": "StandingSave"
                    }
                },
                {
                    "type": {
                        "value": 210,
                        "displayName": "ShotAssist"
                    },
                    "value": "13"
                },
                {
                    "type": {
                        "value": 141,
                        "displayName": "PassEndY"
                    },
                    "value": "81.7"
                },
                {
                    "type": {
                        "value": 56,
                        "displayName": "Zone"
                    },
                    "value": "Left"
                },
                {
                    "type": {
                        "value": 11113,
                        "displayName": "KeyPass"
                    }
                }
            ],
            "satisfiedEventsTypes": [
                91,
                119,
                117,
                30,
                123,
                205,
                40,
                46,
                35,
                37,
                217,
                218
            ],
            "isTouch": true,
            "endX": 86.4,
            "endY": 81.7
        },
        {
            "id": 2636709721.0,
            "eventId": 602,
            "minute": 70,
            "second": 52,
            "teamId": 495,
            "playerId": 427283,
            "relatedEventId": 603,
            "relatedPlayerId": 389409,
            "x": 0.0,
            "y": 0.0,
            "expandedMinute": 74,
            "period": {
                "value": 2,
                "displayName": "SecondHalf"
            },
            "type": {
                "value": 18,
                "displayName": "SubstitutionOff"
            },
            "outcomeType": {
                "value": 1,
                "displayName": "Successful"
            },
            "qualifiers": [
                {
                    "type": {
                        "value": 59,
                        "displayName": "JerseyNumber"
                    },
                    "value": "16"
                },
                {
                    "type": {
                        "value": 44,
                        "displayName": "PlayerPosition"
                    },
                    "value": "Forward"
                },
                {
                    "type": {
                        "value": 55,
                        "displayName": "RelatedEventId"
                    },
                    "value": "603"
                }
            ],
            "satisfiedEventsTypes": [
                214
            ],
            "isTouch": false
        }
    ]
}